{
  "date": "2026-03-16",
  "market_summary": {
    "jp": "日股因中東衝突與油價飆升大幅回檔，日經 225 自 2 月高點 59,332 回落至 53,138（-10.4%）。BOJ 維持利率 0.75% 不變，市場預期 4 月可能升息。日圓貶至 159.5 兌美元，接近 160 干預關卡。VIX 升至 27，市場恐慌情緒偏高。多數個股處於超賣區間，提供逢低布局機會。"
  },
  "scoring_methodology": {
    "description": "MDVI v3 六維度評估框架 + CFA 標準估值方法。六維度確保分析的完整性，目標價由 Forward PE + EV/EBITDA + DCF 三角交叉驗證推導。",
    "model": "MDVI v3 (Multi-Dimensional Valuation Integration)",
    "valuation_method": "Dynamic Justified PE (Primary) + EV/EBITDA & DCF Verification Layers",
    "screening_method": "3-Layer Funnel: Quantitative Hard Filter → Multi-Dimension Quick Score → Full CFA Analysis",
    "dimensions": [
      {
        "name": "基本面 Fundamental",
        "evaluates": "獲利能力 + 財務健康 + 競爭定位",
        "valuation_role": "影響 EPS 假設、WACC、PE 溢價"
      },
      {
        "name": "產業展望 Industry",
        "evaluates": "TAM + 產品發展性 + 客戶價值鏈 + 政策",
        "valuation_role": "影響營收成長率、倍數選擇"
      },
      {
        "name": "總經 Macro",
        "evaluates": "利率/通膨/匯率 + 客戶端總經",
        "valuation_role": "影響 Rf/ERP/PE 水準"
      },
      {
        "name": "技術面 Technical",
        "evaluates": "MA/RSI/KD/量價",
        "valuation_role": "僅影響進場時機"
      },
      {
        "name": "籌碼面 Chip",
        "evaluates": "法人動向/融資券",
        "valuation_role": "僅影響進場時機"
      },
      {
        "name": "消息面 Catalyst",
        "evaluates": "重大消息/催化劑",
        "valuation_role": "修正 EPS 假設或風險溢價"
      }
    ]
  },
  "screening_funnel": {
    "layer1_universe": 228,
    "layer1_pass": 148,
    "layer1_criteria": "PE 1-80, ROE>5%, AvgVol>200K, MarketCap>¥50B",
    "layer2_scored": 148,
    "layer2_pass": 20,
    "layer3_analyzed": 10,
    "layer3_final": 5,
    "industry_diversification": "Auto 1檔, Insurance 1檔, Pharma 1檔, Rail 1檔, Chemicals 1檔"
  },
  "watchlist": [
    {
      "ticker": "4507.T",
      "name": "Shionogi",
      "reason": "Xocova FDA 決定 6 月，等待催化劑"
    },
    {
      "ticker": "8411.T",
      "name": "Mizuho Financial",
      "reason": "BOJ 升息受惠者，等待 4 月升息確認"
    },
    {
      "ticker": "6098.T",
      "name": "Recruit Holdings",
      "reason": "PE 偏高但 ROE 優異，等股價修正更多"
    }
  ],
  "macro_overview": {
    "boj_rate": "0.75%",
    "jp_10y": "2.24%",
    "fed_rate": "3.50-3.75%",
    "us_10y": "4.28%",
    "vix": "27.19",
    "usd_jpy": "159.5",
    "erp_us_base": "4.23%",
    "erp_jp_crp": "0.60%",
    "overall_score": "5/10",
    "summary": "中東衝突推升油價與 VIX，日圓承壓貶至 159.5，BOJ 3 月維持不動但 4 月可能升息。全球風險偏好下降，但日股估值已修正至合理區間，超賣個股出現逢低機會。油價風險為日本進口依賴國最大不確定因素。",
    "tw_10y": "2.24%"
  },
  "sources": [
    "https://tradingeconomics.com/japan/government-bond-yield",
    "https://pages.stern.nyu.edu/~adamodar/New_Home_Page/datafile/ctryprem.html",
    "https://www.boj.or.jp/en/mopo/mpmsche_minu/index.htm",
    "https://finance.yahoo.com/",
    "https://www.investing.com/"
  ],
  "jp_picks": [
    {
      "rank": 1,
      "ticker": "7269.T",
      "name": "鈴木汽車",
      "name_en": "Suzuki Motor Corporation",
      "market": "JP",
      "price": 1900,
      "currency": "JPY",
      "rating": "Strong Buy",
      "entry_signal": "RSI 超賣區間 27.2，股價跌至 52 週低點附近，印度市場長期成長題材未變",
      "target_price": 2435,
      "target_price_basis": "Trailing PE 12.0x × Actual EPS ¥202.83",
      "upside": "+28.2%",
      "scores": {
        "fundamental": 8,
        "industry": 9,
        "macro": 6,
        "technical": 7,
        "valuation": 9,
        "catalyst": 8,
        "chip": 6
      },
      "total_score": 44,
      "summary": "印度汽車市場龍頭 Maruti Suzuki 母公司，PE 僅 9.4x，RSI 深度超賣，Kharkhoda 新廠 2026 年 4 月投產為重大催化劑",
      "report_url": "reports/picks/7269.T-2026-03-16.html",
      "valuation_summary": {
        "valuation_type": "PE",
        "valuation_reason": "",
        "pe_method": "",
        "coe_params": {},
        "growth_params": {},
        "justified_pe": 0,
        "forward_eps": 0,
        "pe_target": 0,
        "ev_ebitda_target": 0,
        "ev_ebitda_deviation": "",
        "dcf_target": 0,
        "dcf_deviation": "",
        "dcf_note": "",
        "dcf_wacc": "",
        "dcf_terminal_growth": "",
        "gordon_pb": {},
        "financial_health": {}
      }
    },
    {
      "rank": 2,
      "ticker": "8766.T",
      "name": "東京海上控股",
      "name_en": "Tokio Marine Holdings",
      "market": "JP",
      "price": 5896,
      "currency": "JPY",
      "rating": "Buy",
      "entry_signal": "RSI 33.5 偏低，股價自高點回落 11%，殖利率 3.6% 提供下檔保護",
      "target_price": 7145,
      "target_price_basis": "Trailing PE 13.0x × Actual EPS ¥549.76",
      "upside": "+21.2%",
      "scores": {
        "fundamental": 9,
        "industry": 8,
        "macro": 6,
        "technical": 7,
        "valuation": 8,
        "catalyst": 7,
        "chip": 6
      },
      "total_score": 43,
      "summary": "日本三大損保龍頭，ROE 20.7%，積極回購+股利（殖利率 3.6%），受惠保費調漲與國際業務成長",
      "report_url": "reports/picks/8766.T-2026-03-16.html",
      "valuation_summary": {
        "valuation_type": "PE",
        "valuation_reason": "",
        "pe_method": "",
        "coe_params": {},
        "growth_params": {},
        "justified_pe": 0,
        "forward_eps": 0,
        "pe_target": 0,
        "ev_ebitda_target": 0,
        "ev_ebitda_deviation": "",
        "dcf_target": 0,
        "dcf_deviation": "",
        "dcf_note": "",
        "dcf_wacc": "",
        "dcf_terminal_growth": "",
        "gordon_pb": {},
        "financial_health": {}
      }
    },
    {
      "rank": 3,
      "ticker": "4568.T",
      "name": "第一三共",
      "name_en": "Daiichi Sankyo Company",
      "market": "JP",
      "price": 2774,
      "currency": "JPY",
      "rating": "Strong Buy",
      "entry_signal": "股價自高點 ¥4,178 回落 33%，分析師共識目標 ¥4,787，Enhertu 持續放量",
      "target_price": 3594,
      "target_price_basis": "Trailing PE 24.0x × Actual EPS ¥149.66",
      "upside": "+29.6%",
      "scores": {
        "fundamental": 8,
        "industry": 9,
        "macro": 6,
        "technical": 7,
        "valuation": 7,
        "catalyst": 9,
        "chip": 6
      },
      "total_score": 45,
      "summary": "全球 ADC 抗癌藥物領導者，Enhertu 營收 ¥552.8B 持續高成長，5 款 ADC 2026 年將上市，股價已大幅修正提供進場機會",
      "report_url": "reports/picks/4568.T-2026-03-16.html",
      "valuation_summary": {
        "valuation_type": "PE",
        "valuation_reason": "",
        "pe_method": "",
        "coe_params": {},
        "growth_params": {},
        "justified_pe": 0,
        "forward_eps": 0,
        "pe_target": 0,
        "ev_ebitda_target": 0,
        "ev_ebitda_deviation": "",
        "dcf_target": 0,
        "dcf_deviation": "",
        "dcf_note": "",
        "dcf_wacc": "",
        "dcf_terminal_growth": "",
        "gordon_pb": {},
        "financial_health": {}
      }
    },
    {
      "rank": 4,
      "ticker": "9022.T",
      "name": "JR 東海",
      "name_en": "Central Japan Railway",
      "market": "JP",
      "price": 4242,
      "currency": "JPY",
      "rating": "Buy",
      "entry_signal": "RSI 23.0 極度超賣，PB 0.82 低於帳面價值，東海道新幹線復甦題材",
      "target_price": 5334,
      "target_price_basis": "Trailing PE 10.0x × Actual EPS ¥533.41",
      "upside": "+25.7%",
      "scores": {
        "fundamental": 8,
        "industry": 7,
        "macro": 6,
        "technical": 8,
        "valuation": 9,
        "catalyst": 7,
        "chip": 7
      },
      "total_score": 43,
      "summary": "東海道新幹線獨佔營運者，PB 僅 0.82x，RSI 極度超賣 23.0，訪日旅客帶動客運量持續回升，磁浮列車 2034 完工為長期催化劑",
      "report_url": "reports/picks/9022.T-2026-03-16.html",
      "valuation_summary": {
        "valuation_type": "PE",
        "valuation_reason": "",
        "pe_method": "",
        "coe_params": {},
        "growth_params": {},
        "justified_pe": 0,
        "forward_eps": 0,
        "pe_target": 0,
        "ev_ebitda_target": 0,
        "ev_ebitda_deviation": "",
        "dcf_target": 0,
        "dcf_deviation": "",
        "dcf_note": "",
        "dcf_wacc": "",
        "dcf_terminal_growth": "",
        "gordon_pb": {},
        "financial_health": {}
      }
    },
    {
      "rank": 5,
      "ticker": "4005.T",
      "name": "住友化學",
      "name_en": "Sumitomo Chemical Co.",
      "market": "JP",
      "price": 487,
      "currency": "JPY",
      "rating": "Buy",
      "entry_signal": "PB 0.77x 低於帳面價值，EPS 轉虧為盈，RSI 31.3 偏低",
      "target_price": 622,
      "target_price_basis": "Trailing PE 12.0x × Actual EPS ¥51.84",
      "upside": "+27.7%",
      "scores": {
        "fundamental": 7,
        "industry": 7,
        "macro": 5,
        "technical": 7,
        "valuation": 8,
        "catalyst": 7,
        "chip": 6
      },
      "total_score": 39,
      "summary": "化學大廠轉虧為盈，PB 0.77x 低於帳面價值，Q3 營業利益 +211% YoY，半導體材料需求帶動復甦",
      "report_url": "reports/picks/4005.T-2026-03-16.html",
      "valuation_summary": {
        "valuation_type": "PE",
        "valuation_reason": "",
        "pe_method": "",
        "coe_params": {},
        "growth_params": {},
        "justified_pe": 0,
        "forward_eps": 0,
        "pe_target": 0,
        "ev_ebitda_target": 0,
        "ev_ebitda_deviation": "",
        "dcf_target": 0,
        "dcf_deviation": "",
        "dcf_note": "",
        "dcf_wacc": "",
        "dcf_terminal_growth": "",
        "gordon_pb": {},
        "financial_health": {}
      }
    }
  ],
  "jp_count": 5
}